Metadata-Version: 2.1
Name: pacotepypi1235
Version: 0.0.1
Summary: Pacote python para exibir número de 1 a 9
Home-page: https://github.com/Fabreba/pypacotinho.git
Author: Fabricio José Sousa Silva
Author-email: fabricioj49@gmail.com
License: MIT License
Keywords: Pacote
License-File: LICENSE
